maya_brew/__init__.py
maya_brew/exceptions.py
maya_brew/log.py
maya_brew/scene.py
maya_brew/utils.py
maya_brew/attributes/__init__.py
maya_brew/attributes/node_attribute.py
maya_brew/maya_initializer/__init__.py
maya_brew/maya_initializer/interactive_init.py
maya_brew/maya_initializer/interactive_utils.py
maya_brew/maya_initializer/shared.py
maya_brew/maya_initializer/standalone_init.py
maya_brew/nodes/__init__.py
maya_brew/nodes/cast.py
maya_brew/nodes/node_types.py
maya_brew-0.0.5.dist-info/METADATA
maya_brew-0.0.5.dist-info/WHEEL
maya_brew-0.0.5.dist-info/licenses/LICENSE
maya_brew-0.0.5.dist-info/RECORD
