Metadata-Version: 2.4
Name: maya-brew
Version: 0.0.5
Summary: Safe interaction with python in maya
Project-URL: Homepage, https://github.com/mortenbohne/maya-brew
Project-URL: Repository, https://github.com/mortenbohne/maya-brew
Project-URL: Documentation, https://github.com/mortenbohne/maya-brew#readme
Project-URL: Issues, https://github.com/mortenbohne/maya-brew/issues
Project-URL: Changelog, https://github.com/mortenbohne/maya-brew/releases
Author-email: Morten Bøhne <github@mortenbohne.dk>
License-Expression: MIT
License-File: LICENSE
Keywords: 3d,autodesk,maya,pipeline
Classifier: Development Status :: 2 - Pre-Alpha
Classifier: Intended Audience :: Developers
Classifier: Programming Language :: Python :: 3
Classifier: Programming Language :: Python :: 3.11
Classifier: Programming Language :: Python :: 3.12
Classifier: Topic :: Multimedia :: Graphics :: 3D Modeling
Requires-Python: >=3.11
Requires-Dist: colorama
Requires-Dist: structlog
Provides-Extra: dev
Requires-Dist: maya-stubs; extra == 'dev'
Requires-Dist: pytest; extra == 'dev'
